[
  {
    "name": "Gaul",
    "filePath": "HytharaPlanetPack v0.1.2\\GameData\\PlanetXpack\\KopernicusFiles\\Gaul.cfg"
  },
  {
    "name": "Hythara",
    "filePath": "HytharaPlanetPack v0.1.2\\GameData\\PlanetXpack\\KopernicusFiles\\Hythara.cfg"
  },
  {
    "name": "Nemesis",
    "filePath": "HytharaPlanetPack v0.1.2\\GameData\\PlanetXpack\\KopernicusFiles\\Nemesis.cfg"
  },
  {
    "name": "Niran",
    "filePath": "HytharaPlanetPack v0.1.2\\GameData\\PlanetXpack\\KopernicusFiles\\Niran.cfg"
  },
  {
    "name": "Riaz",
    "filePath": "HytharaPlanetPack v0.1.2\\GameData\\PlanetXpack\\KopernicusFiles\\Riaz.cfg"
  }
]