[
  {
    "name": "radialomniseparator-003125",
    "filePath": "nli2work\\RadialOmniSeparator\\Parts\\ros-003125.cfg"
  },
  {
    "name": "radialomniseparator-00625",
    "filePath": "nli2work\\RadialOmniSeparator\\Parts\\ros-00625.cfg"
  },
  {
    "name": "radialomniseparator-0125",
    "filePath": "nli2work\\RadialOmniSeparator\\Parts\\ros-0125.cfg"
  },
  {
    "name": "radialomniseparator-01875",
    "filePath": "nli2work\\RadialOmniSeparator\\Parts\\ros-01875.cfg"
  },
  {
    "name": "radialomniseparator-0250",
    "filePath": "nli2work\\RadialOmniSeparator\\Parts\\ros-0250.cfg"
  },
  {
    "name": "radialomniseparator-0375",
    "filePath": "nli2work\\RadialOmniSeparator\\Parts\\ros-0375.cfg"
  }
]