[
  {
    "name": "legacy_engine",
    "filePath": "SciFi\\_Legacy\\Parts\\Engines\\engine.cfg"
  },
  {
    "name": "legacy_enginegimbal",
    "filePath": "SciFi\\_Legacy\\Parts\\Engines\\gimbalengine.cfg"
  },
  {
    "name": "legacy_enginegimbalsmall",
    "filePath": "SciFi\\_Legacy\\Parts\\Engines\\gimbalenginesmall.cfg"
  },
  {
    "name": "LegacyPod",
    "filePath": "SciFi\\_Legacy\\Parts\\Pod\\part.cfg"
  },
  {
    "name": "legacy_smalltank",
    "filePath": "SciFi\\_Legacy\\Parts\\Tanks\\smalltank.cfg"
  },
  {
    "name": "legacy_tank",
    "filePath": "SciFi\\_Legacy\\Parts\\Tanks\\tank.cfg"
  },
  {
    "name": "LegacyInternal",
    "filePath": "SciFi\\_Legacy\\Spaces\\Pod\\internal.cfg"
  }
]